template_partials/__init__.py
template_partials/apps.py
template_partials/loader.py
template_partials/templatetags/__init__.py
template_partials/templatetags/partials.py
django_template_partials-24.3.dist-info/LICENSE
django_template_partials-24.3.dist-info/WHEEL
django_template_partials-24.3.dist-info/METADATA
django_template_partials-24.3.dist-info/RECORD
