Metadata-Version: 2.1
Name: django-template-partials
Version: 24.3
Summary: django-template-partials
Author-email: Carlton Gibson <carlton.gibson@noumenal.es>
Classifier: License :: OSI Approved :: MIT License
Classifier: Development Status :: 4 - Beta
Classifier: Programming Language :: Python
Classifier: Programming Language :: Python :: 3
Classifier: Programming Language :: Python :: 3.10
Classifier: Programming Language :: Python :: 3.11
Classifier: Programming Language :: Python :: 3.12
Classifier: Framework :: Django
Classifier: Framework :: Django :: 4.2
Classifier: Framework :: Django :: 5.0
Classifier: Framework :: Django :: 5.1
Requires-Dist: Django
Requires-Dist: Sphinx ; extra == "docs"
Requires-Dist: coverage ; extra == "tests"
Requires-Dist: django_coverage_plugin ; extra == "tests"
Project-URL: Changelog, https://github.com/carltongibson/django-template-partials/blob/main/CHANGELOG.md
Project-URL: Docs, https://github.com/carltongibson/django-template-partials?tab=readme-ov-file#basic-usage
Project-URL: Repository, https://github.com/carltongibson/django-template-partials/
Provides-Extra: docs
Provides-Extra: tests
